crea_lib-0.1.3.dist-info/METADATA
crea_lib-0.1.3.dist-info/RECORD
crea_lib-0.1.3.dist-info/WHEEL
crea_lib-0.1.3.dist-info/top_level.txt
creapy/__init__.py
creapy/account.py
creapy/aes.py
creapy/amount.py
creapy/block.py
creapy/blockchain.py
creapy/blog.py
creapy/converter.py
creapy/crea.py
creapy/data.py
creapy/dex.py
creapy/exceptions.py
creapy/instance.py
creapy/post.py
creapy/profile.py
creapy/savings.py
creapy/storage.py
creapy/transactionbuilder.py
creapy/utils.py
creapy/wallet.py
creapy/witness.py
creapyapi/__init__.py
creapyapi/creaasyncclient.py
creapyapi/creaclient.py
creapyapi/creanoderpc.py
creapyapi/creawalletrpc.py
creapyapi/exceptions.py
creapybase/__init__.py
creapybase/account.py
creapybase/chains.py
creapybase/memo.py
creapybase/objecttypes.py
creapybase/operationids.py
creapybase/operations.py
creapybase/signedtransactions.py
creapybase/transactions.py
