Metadata-Version: 2.1
Name: crea-lib
Version: 0.1.3
Summary: Python library for Crea
Home-page: http://library.creas.io/crea-python-lib
Author: Creativechain Foundation
Author-email: info@creativechain.org
Maintainer: Creativechain Foundation
Maintainer-email: info@creativechain.org
License: UNKNOWN
Download-URL: https://github.com/creativechain/crea-python-lib/tarball/0.1.3
Keywords: crea,library,api,rpc,transactions
Platform: UNKNOWN
Classifier: License :: OSI Approved :: MIT License
Classifier: Operating System :: OS Independent
Classifier: Programming Language :: Python :: 3
Classifier: Development Status :: 3 - Alpha
Classifier: Intended Audience :: Developers
Classifier: Intended Audience :: Financial and Insurance Industry
Classifier: Topic :: Office/Business :: Financial
Requires-Dist: crea-graphenelib (>=0.1.3)
Requires-Dist: websockets (>=2.0)
Requires-Dist: scrypt (>=0.7.1)
Requires-Dist: diff-match-patch (>=20121119)
Requires-Dist: appdirs (>=1.4.0)
Requires-Dist: python-frontmatter (>=0.2.1)
Requires-Dist: pycrypto (>=2.6.1)
Requires-Dist: funcy
Requires-Dist: python-dateutil (>=2.6.1)
